jovian/__init__.py
jovian/_flavor.py
jovian/_version.py
jovian/cli.py
jovian/callbacks/__init__.py
jovian/callbacks/fastai.py
jovian/callbacks/keras.py
jovian/jovian_nb_ext/README.md
jovian/jovian_nb_ext/description.yml
jovian/jovian_nb_ext/jovian_nb_ext.json
jovian/jovian_nb_ext/main.js
jovian/tests/__init__.py
jovian/tests/test_install.py
jovian/utils/__init__.py
jovian/utils/anaconda.py
jovian/utils/api.py
jovian/utils/clone.py
jovian/utils/configure.py
jovian/utils/constants.py
jovian/utils/credentials.py
jovian/utils/envfile.py
jovian/utils/install.py
jovian/utils/jupyter.py
jovian/utils/logger.py
jovian/utils/misc.py
jovian/utils/pip.py
jovian/utils/rcfile.py
jovian/utils/slack.py
jovianpro-0.1.82.data/data/etc/jupyter/nbconfig/notebook.d/jovian_nb_ext.json
jovianpro-0.1.82.data/data/share/jupyter/nbextensions/jovian_nb_ext/main.js
jovianpro-0.1.82.dist-info/METADATA
jovianpro-0.1.82.dist-info/RECORD
jovianpro-0.1.82.dist-info/WHEEL
jovianpro-0.1.82.dist-info/entry_points.txt
jovianpro-0.1.82.dist-info/top_level.txt
