Metadata-Version: 2.1
Name: jovianpro
Version: 0.1.82
Summary: Jovian Python SDK
Home-page: https://swiftace.ai/
Author: SwiftAce
Author-email: opensource@swiftace.ai
License: UNKNOWN
Platform: UNKNOWN
Classifier: Programming Language :: Python :: 3
Classifier: License :: OSI Approved :: MIT License
Classifier: Operating System :: OS Independent
Requires-Dist: requests
Requires-Dist: uuid
Requires-Dist: pyyaml
